sr.tools-1.2.0-py3.8-nspkg.pth
sr/tools/__init__.py
sr/tools/budget.py
sr/tools/config.py
sr/tools/environment.py
sr/tools/spending.py
sr/tools/teamgit.py
sr/tools/trac.py
sr/tools/bom/__init__.py
sr/tools/bom/bom.py
sr/tools/bom/cachedfetch.py
sr/tools/bom/component_lib.csv
sr/tools/bom/digikey.py
sr/tools/bom/distpart.py
sr/tools/bom/farnell.py
sr/tools/bom/geda.py
sr/tools/bom/mouser.py
sr/tools/bom/parts_db.py
sr/tools/bom/rs.py
sr/tools/bom/schem.py
sr/tools/bom/threadpool.py
sr/tools/cli/__init__.py
sr/tools/cli/__main__.py
sr/tools/cli/bom_header.html
sr/tools/cli/budget_check.py
sr/tools/cli/budget_close.py
sr/tools/cli/budget_diff.py
sr/tools/cli/budget_eval.py
sr/tools/cli/budget_query.py
sr/tools/cli/budget_tree.py
sr/tools/cli/cam_serial.py
sr/tools/cli/check_my_git.py
sr/tools/cli/clone.py
sr/tools/cli/clone_team.py
sr/tools/cli/comp_calculate_league_matches.py
sr/tools/cli/create_bom.py
sr/tools/cli/create_order.py
sr/tools/cli/digikey.py
sr/tools/cli/document.py
sr/tools/cli/document_prefix.tex
sr/tools/cli/document_suffix.tex
sr/tools/cli/export_gerber.py
sr/tools/cli/farnell.py
sr/tools/cli/geda_hierpcb.py
sr/tools/cli/got_mcf.py
sr/tools/cli/help.py
sr/tools/cli/ide_list_repos.py
sr/tools/cli/ide_list_teams.py
sr/tools/cli/ide_version.py
sr/tools/cli/inv_edit.py
sr/tools/cli/inv_findpart.py
sr/tools/cli/inv_history.py
sr/tools/cli/inv_list_assy_templates.py
sr/tools/cli/inv_list_templates.py
sr/tools/cli/inv_mv.py
sr/tools/cli/inv_new_asset.py
sr/tools/cli/inv_new_group.py
sr/tools/cli/inv_query.py
sr/tools/cli/inv_set_attr.py
sr/tools/cli/inv_show.py
sr/tools/cli/inv_show_parent.py
sr/tools/cli/inv_sync_asset.py
sr/tools/cli/inv_touch.py
sr/tools/cli/inv_validate.py
sr/tools/cli/latex-assets.zip
sr/tools/cli/ledger.py
sr/tools/cli/list_commands.py
sr/tools/cli/make_purchase.py
sr/tools/cli/mcv4b_part_code.py
sr/tools/cli/mouser.py
sr/tools/cli/pcb_lint.py
sr/tools/cli/pcb_to_thou.py
sr/tools/cli/price_graph.py
sr/tools/cli/repolist.py
sr.tools-1.2.0.dist-info/LICENSE.rst
sr.tools-1.2.0.dist-info/METADATA
sr.tools-1.2.0.dist-info/WHEEL
sr.tools-1.2.0.dist-info/entry_points.txt
sr.tools-1.2.0.dist-info/namespace_packages.txt
sr.tools-1.2.0.dist-info/top_level.txt
sr.tools-1.2.0.dist-info/RECORD
